{
  "manifest": {
    "apis": {
      "custom": {
        "endpoint": {
          "uri": "arn:aws:lambda:us-east-1:333994905369:function:c6fffb0c-b56b-4226-a66b-2b2b6b75274a:Release_0"
        },
        "interfaces": [],
        "regions": {
          "NA": {
            "endpoint": {
              "uri": "arn:aws:lambda:us-east-1:333994905369:function:c6fffb0c-b56b-4226-a66b-2b2b6b75274a:Release_0"
            }
          },
          "EU": {
            "endpoint": {
              "uri": "arn:aws:lambda:eu-west-1:333994905369:function:c6fffb0c-b56b-4226-a66b-2b2b6b75274a:Release_0"
            }
          },
          "FE": {
            "endpoint": {
              "uri": "arn:aws:lambda:us-west-2:333994905369:function:c6fffb0c-b56b-4226-a66b-2b2b6b75274a:Release_0"
            }
          }
        }
      }
    },
    "manifestVersion": "1.0",
    "permissions": [
      {
        "name": "alexa::devices:all:geolocation:read"
      }
    ],
    "privacyAndCompliance": {
      "locales": {
        "en-US": {}
      }
    },
    "publishingInformation": {
      "automaticDistribution": {
        "isActive": false
      },
      "category": "CONNECTED_CAR",
      "distributionCountries": [],
      "isAvailableWorldwide": true,
      "locales": {
        "en-US": {
          "description": "Sample Full Description",
          "examplePhrases": [
            "Alexa open accident guide",
            "File a claim",
            "Someone is injured"
          ],
          "keywords": [],
          "name": "Accident Guide",
          "summary": "Sample Short Description"
        }
      },
      "testingInstructions": "Sample Testing Instructions."
    }
  }
}